<?xml version="1.0" encoding="UTF-8"?>
<objects serializationModel="Studio.02.00.00">
	<object class="AudioFile" id="{a83d3ca8-eaf7-4a72-bfd0-5cb67b0fe3b3}">
		<property name="assetPath">
			<value>radio1.wav</value>
		</property>
		<property name="isStreaming">
			<value>true</value>
		</property>
		<property name="frequencyInKHz">
			<value>8</value>
		</property>
		<property name="channelCount">
			<value>1</value>
		</property>
		<property name="length">
			<value>17.854624999999999</value>
		</property>
		<relationship name="masterAssetFolder">
			<destination>{b8846c50-76ec-4571-abbc-4d64c185a916}</destination>
		</relationship>
	</object>
</objects>
